gexfpy/__init__.py
gexfpy/datatypes.py
gexfpy/dynamics.py
gexfpy/gexf.py
gexfpy/gexfparser.py
gexfpy/phylogenics.py
gexfpy/viz.py
gexfpy-0.1.1.dist-info/LICENSE
gexfpy-0.1.1.dist-info/METADATA
gexfpy-0.1.1.dist-info/WHEEL
gexfpy-0.1.1.dist-info/top_level.txt
gexfpy-0.1.1.dist-info/RECORD
