Metadata-Version: 2.1
Name: gexfpy
Version: 0.1.1
Summary: An Python Class for Generate gexf format graph description file for gephi.
Home-page: https://github.com/chunqishi/gexfpy
Author: Chunqi Shi
Author-email: scq830@163.com
License: MIT License
Keywords: gexf,graph visualization,gephi
Platform: UNKNOWN
Classifier: Development Status :: 3 - Alpha
Classifier: Intended Audience :: Science/Research
Classifier: Intended Audience :: Developers
Classifier: Topic :: Scientific/Engineering :: Artificial Intelligence
Classifier: License :: OSI Approved :: MIT License
Classifier: Programming Language :: Python :: 3
Classifier: Programming Language :: Python :: 3.6
Classifier: Programming Language :: Python :: 3.7
Classifier: Programming Language :: Python :: 3.8
Requires-Dist: xsdata (==21.9)
Requires-Dist: matplotlib (>=3.3.2)
